webtask/__init__.py
webtask/main.py
webtask/server.py
webtask/static/command-icons.css
webtask/static/config.json
webtask/static/favicon.ico
webtask/static/file-icons.css
webtask/static/file-system.js
webtask/static/index.html
webtask/static/js/modules/core.js
webtask/static/js/modules/file-system-manager.js
webtask/static/js/modules/process-manager.js
webtask/static/js/modules/system-monitor.js
webtask/static/js/modules/ui-manager.js
webtask/static/js/webtask.js
webtask/static/manifest.json
webtask/static/process-data.js
webtask/static/styles.css
webtask/static/webtask.js
webtask/static/webtask.js.bak
webtask-2.0.6.dist-info/LICENSE
webtask-2.0.6.dist-info/METADATA
webtask-2.0.6.dist-info/WHEEL
webtask-2.0.6.dist-info/entry_points.txt
webtask-2.0.6.dist-info/RECORD
