Metadata-Version: 2.3
Name: webtask
Version: 2.0.6
Summary: A modern, web-based system monitor inspired by htop with file browser and process transparency
Keywords: system,monitor,htop,web,processes,file-browser,transparency
Author: Tom Sapletta
Author-email: info@softreck.dev
Requires-Python: >=3.8.1,<4.0.0
Classifier: Development Status :: 4 - Beta
Classifier: Environment :: Web Environment
Classifier: Intended Audience :: Developers
Classifier: Intended Audience :: System Administrators
Classifier: License :: OSI Approved :: MIT License
Classifier: Operating System :: OS Independent
Classifier: Programming Language :: Python :: 3
Classifier: Programming Language :: Python :: 3.9
Classifier: Programming Language :: Python :: 3.10
Classifier: Programming Language :: Python :: 3.11
Classifier: Programming Language :: Python :: 3.12
Classifier: Programming Language :: Python :: 3.13
Classifier: Programming Language :: Python :: 3.7
Classifier: Programming Language :: Python :: 3.8
Classifier: Topic :: Internet :: WWW/HTTP :: Browsers
Classifier: Topic :: System :: Monitoring
Classifier: Topic :: System :: Systems Administration
Requires-Dist: psutil (>=5.9.0,<6.0.0)
Project-URL: Documentation, https://github.com/devopsterminal/webtask
Project-URL: Homepage, https://github.com/devopsterminal/webtask
Project-URL: Repository, https://github.com/devopsterminal/webtask
